responsible_ai_datacleaner/__init__.py
responsible_ai_datacleaner/text_cleaner.py
responsible_ai_datacleaner-0.0.9.dist-info/LICENSE
responsible_ai_datacleaner-0.0.9.dist-info/METADATA
responsible_ai_datacleaner-0.0.9.dist-info/WHEEL
responsible_ai_datacleaner-0.0.9.dist-info/top_level.txt
responsible_ai_datacleaner-0.0.9.dist-info/RECORD
