Metadata-Version: 2.1
Name: responsible-ai-datacleaner
Version: 0.0.9
Summary: Package that can clean text for the resp-ai project
Home-page: http://pypi.python.org/pypi/responsible_ai_datacleaner/
Author: Sem
Author-email: no@example.com
License: LICENSE.txt
Platform: UNKNOWN
License-File: LICENSE
Requires-Dist: nltk
Requires-Dist: tweet-preprocessor
Requires-Dist: pandas
Requires-Dist: emoji
